ecreshore/__init__.py
ecreshore/async_docker_client.py
ecreshore/aws_utils.py
ecreshore/cache_config.py
ecreshore/ecr_auth.py
ecreshore/terminal_detection.py
ecreshore/cli/__init__.py
ecreshore/cli/cluster/__init__.py
ecreshore/cli/cluster/inspect.py
ecreshore/cli/cluster/scan.py
ecreshore/cli/cluster/scan_formatters.py
ecreshore/cli/cluster/scan_helpers.py
ecreshore/cli/core/__init__.py
ecreshore/cli/core/auth_test.py
ecreshore/cli/core/batch.py
ecreshore/cli/core/copy.py
ecreshore/cli/repository/__init__.py
ecreshore/cli/repository/list_images.py
ecreshore/cli/repository/list_repositories.py
ecreshore/cli/repository/purge.py
ecreshore/cli/tools/__init__.py
ecreshore/cli/tools/completion.py
ecreshore/cli/tools/generate_config.py
ecreshore/cli/tools/terminal_info.py
ecreshore/cli/utils/__init__.py
ecreshore/cli/utils/completion.py
ecreshore/cli/utils/logging_setup.py
ecreshore/cli/utils/ui_helpers.py
ecreshore/cli/utils/validation.py
ecreshore/services/__init__.py
ecreshore/services/async_transfer_service.py
ecreshore/services/base_service.py
ecreshore/services/batch_config.py
ecreshore/services/batch_error_aggregator.py
ecreshore/services/batch_processor.py
ecreshore/services/batch_progress.py
ecreshore/services/buildx_transfer_service.py
ecreshore/services/cache_backends.py
ecreshore/services/cache_manager.py
ecreshore/services/cache_service.py
ecreshore/services/digest_verification.py
ecreshore/services/ecr_repository.py
ecreshore/services/error_handler.py
ecreshore/services/hybrid_transfer_service.py
ecreshore/services/image_parser.py
ecreshore/services/image_presence_checker.py
ecreshore/services/k8s_config.py
ecreshore/services/k8s_models.py
ecreshore/services/k8s_scanner.py
ecreshore/services/output_modes.py
ecreshore/services/platform_models.py
ecreshore/services/progress_reporter.py
ecreshore/services/purge_service.py
ecreshore/services/resume_service.py
ecreshore/services/retry_service.py
ecreshore/services/single_transfer_progress.py
ecreshore-1.0.1.dist-info/METADATA
ecreshore-1.0.1.dist-info/WHEEL
ecreshore-1.0.1.dist-info/entry_points.txt
ecreshore-1.0.1.dist-info/top_level.txt
ecreshore-1.0.1.dist-info/RECORD
