Metadata-Version: 2.4
Name: ecreshore
Version: 1.0.1
Summary: cli utility for copying container images to private ECR
Requires-Python: >=3.10
Requires-Dist: aiodocker==0.24.0
Requires-Dist: boto3==1.40.25
Requires-Dist: click==8.2.1
Requires-Dist: docker==7.1.0
Requires-Dist: kubernetes==33.1.0
Requires-Dist: pytest-asyncio>=1.1.0
Requires-Dist: pytest-cov>=7.0.0
Requires-Dist: radon>=6.0.1
Requires-Dist: rich==14.1.0
Requires-Dist: structlog==25.4.0
Requires-Dist: tenacity==9.1.2
Requires-Dist: yaml-for-humans==1.1.1
